ifcopenshell/__init__.py
ifcopenshell/_ifcopenshell_wrapper.cpython-312-darwin.so
ifcopenshell/draw.py
ifcopenshell/entity_instance.py
ifcopenshell/file.py
ifcopenshell/guid.py
ifcopenshell/ifcopenshell_wrapper.py
ifcopenshell/ifcopenshell_wrapper.pyi
ifcopenshell/py.typed
ifcopenshell/requirements.txt
ifcopenshell/settings.py
ifcopenshell/sql.py
ifcopenshell/stream.py
ifcopenshell/template.py
ifcopenshell/validate.py
ifcopenshell/api/__init__.py
ifcopenshell/api/aggregate/__init__.py
ifcopenshell/api/aggregate/assign_object.py
ifcopenshell/api/aggregate/unassign_object.py
ifcopenshell/api/alignment/__init__.py
ifcopenshell/api/alignment/_add_segment_to_curve.py
ifcopenshell/api/alignment/_add_segment_to_layout.py
ifcopenshell/api/alignment/_add_zero_length_segment.py
ifcopenshell/api/alignment/_create_geometric_representation.py
ifcopenshell/api/alignment/_get_mapped_segments.py
ifcopenshell/api/alignment/_get_segment_start_point_label.py
ifcopenshell/api/alignment/_map_alignment_cant_segment.py
ifcopenshell/api/alignment/_map_alignment_horizontal_segment.py
ifcopenshell/api/alignment/_map_alignment_vertical_segment.py
ifcopenshell/api/alignment/_update_curve_segment_transition_code.py
ifcopenshell/api/alignment/add_stationing_referent.py
ifcopenshell/api/alignment/add_vertical_layout.py
ifcopenshell/api/alignment/create_alignment.py
ifcopenshell/api/alignment/create_by_pi_method.py
ifcopenshell/api/alignment/create_from_csv.py
ifcopenshell/api/alignment/create_layout_segment.py
ifcopenshell/api/alignment/create_segment_representations.py
ifcopenshell/api/alignment/distance_along_from_station.py
ifcopenshell/api/alignment/get_alignment.py
ifcopenshell/api/alignment/get_alignment_layouts.py
ifcopenshell/api/alignment/get_alignment_station.py
ifcopenshell/api/alignment/get_axis_subcontext.py
ifcopenshell/api/alignment/get_basis_curve.py
ifcopenshell/api/alignment/get_cant_layout.py
ifcopenshell/api/alignment/get_child_alignments.py
ifcopenshell-0.8.3.post1.dist-info/METADATA
ifcopenshell-0.8.3.post1.dist-info/WHEEL
ifcopenshell-0.8.3.post1.dist-info/top_level.txt
ifcopenshell-0.8.3.post1.dist-info/RECORD
