Metadata-Version: 2.4
Name: ifcopenshell
Version: 0.8.3.post1
Summary: Python bindings, utility functions, and high-level API for IfcOpenShell
Author-email: Dion Moult <dion@thinkmoult.com>
Project-URL: Homepage, http://ifcopenshell.org
Project-URL: Bug Tracker, https://github.com/ifcopenshell/ifcopenshell/issues
Classifier: Programming Language :: Python :: 3
Classifier: License :: OSI Approved :: GNU Lesser General Public License v3 or later (LGPLv3+)
Requires-Python: <3.13,>=3.9
Requires-Dist: shapely
Requires-Dist: numpy
Requires-Dist: isodate
Requires-Dist: python-dateutil
Requires-Dist: lark
Requires-Dist: typing-extensions
Provides-Extra: advanced
Requires-Dist: networkx; extra == "advanced"
Provides-Extra: dev
Requires-Dist: pytest; extra == "dev"
Requires-Dist: tabulate; extra == "dev"
